quasar_unred/__init__.py
quasar_unred/unred_module.py
quasar_unred-0.18.dist-info/METADATA
quasar_unred-0.18.dist-info/WHEEL
quasar_unred-0.18.dist-info/licenses/LICENSE
quasar_unred-0.18.dist-info/RECORD
