Metadata-Version: 2.1
Name: quasar_unred
Version: 0.18
Summary: Determine the E(B-V) values of observed quasar spectra
Project-URL: Homepage, https://github.com/jackklawitter/quasar_unred
Author-email: John Klawitter <jackklawitter@gmail.com>
License-File: LICENSE
Classifier: License :: OSI Approved :: BSD License
Classifier: Operating System :: OS Independent
Classifier: Programming Language :: Python :: 3
Requires-Python: >=3.9
Requires-Dist: astropy
Requires-Dist: dust-extinction
Requires-Dist: matplotlib
Requires-Dist: numpy
Requires-Dist: scipy
